xcover/__init__.py
xcover/dancing_cells.py
xcover/dancing_cells_zdd.py
xcover/io.py
xcover/solvers.py
xcover/utils.py
xcover/zdd_utils.py
xcover-0.2.5.dist-info/licenses/LICENSE
xcover-0.2.5.dist-info/METADATA
xcover-0.2.5.dist-info/WHEEL
xcover-0.2.5.dist-info/top_level.txt
xcover-0.2.5.dist-info/RECORD
