Metadata-Version: 2.4
Name: xcover
Version: 0.2.5
Summary: Exact cover with colors
Author-email: "John F. Rudge" <jfr23@cam.ac.uk>
Project-URL: Homepage, https://github.com/johnrudge/xcover
Project-URL: Issues, https://github.com/johnrudge/xcover/issues
Classifier: Programming Language :: Python :: 3
Classifier: License :: OSI Approved :: GNU Lesser General Public License v3 (LGPLv3)
Classifier: Operating System :: OS Independent
Requires-Python: >=3.8
License-File: LICENSE
Requires-Dist: numba
Dynamic: license-file
